flask_fastx/__init__.py
flask_fastx/autowire_decorator.py
flask_fastx/model_api.py
flask_fastx/param_funcations.py
flask_fastx/params.py
flask_fastx/parser_api.py
flask_fastx/path_param.py
flask_fastx-0.1.4.dist-info/LICENSE
flask_fastx-0.1.4.dist-info/WHEEL
flask_fastx-0.1.4.dist-info/METADATA
flask_fastx-0.1.4.dist-info/RECORD
