Metadata-Version: 2.1
Name: flask-fastx
Version: 0.1.4
Summary: Flask-Fastx is a Fast API style support for Flask. It Gives you MyPy types with the flexibility of flask.
Home-page: https://github.com/tactful-ai/flask-faster-api
License: MIT
Keywords: flask,flask-restx,Mypy
Author: nadaabdelmaboud     seifashraf1     ahmedihabb2     omargamal253
Requires-Python: >=3.7,<4.0
Classifier: License :: OSI Approved :: MIT License
Classifier: Programming Language :: Python :: 3
Classifier: Programming Language :: Python :: 3.7
Classifier: Programming Language :: Python :: 3.8
Classifier: Programming Language :: Python :: 3.9
Requires-Dist: flask-restx (>=0.5.0,<0.6.0)
Requires-Dist: pydantic (>=1.8.2,<2.0.0)
Project-URL: Repository, https://github.com/tactful-ai/flask-faster-api
